esgf_scraper/__init__.py
esgf_scraper/_version.py
esgf_scraper/checksum.py
esgf_scraper/cli.py
esgf_scraper/config.py
esgf_scraper/contextfactory.py
esgf_scraper/downloader.py
esgf_scraper/items.py
esgf_scraper/middlewares.py
esgf_scraper/pipelines.py
esgf_scraper/postprocess.py
esgf_scraper/settings.py
esgf_scraper/sqlite.py
esgf_scraper/utils.py
esgf_scraper/ext/__init__.py
esgf_scraper/ext/dblite/__init__.py
esgf_scraper/ext/dblite/item.py
esgf_scraper/ext/dblite/query.py
esgf_scraper/ext/dblite/serializers.py
esgf_scraper/ext/dblite/settings.py
esgf_scraper/spiders/__init__.py
esgf_scraper/spiders/download.py
esgf_scraper/spiders/search.py
esgf_scraper-0.4.4.dist-info/LICENSE
esgf_scraper-0.4.4.dist-info/METADATA
esgf_scraper-0.4.4.dist-info/WHEEL
esgf_scraper-0.4.4.dist-info/entry_points.txt
esgf_scraper-0.4.4.dist-info/top_level.txt
esgf_scraper-0.4.4.dist-info/RECORD
