Metadata-Version: 2.1
Name: esgf-scraper
Version: 0.4.4
Summary: Keeps a local data repository in syncronisation with ESGF
Home-page: https://gitlab.com/magicc/esgf-scraper
Author: Jared Lewis
Author-email: jared.lewis@climate-energy-college.org
License: MIT License
Project-URL: Documentation, https://magicc.gitlab.io/esgf-scraper/
Project-URL: Source, https://gitlab.com/magicc/esgf-scraper
Keywords: esgf,cmip6,scrape
Platform: UNKNOWN
Classifier: Development Status :: 4 - Beta
Classifier: License :: OSI Approved :: MIT License
Classifier: Intended Audience :: Developers
Classifier: Operating System :: OS Independent
Classifier: Programming Language :: Python :: 3.6
Classifier: Programming Language :: Python :: 3.7
Requires-Dist: click
Requires-Dist: scrapy
Requires-Dist: esgf-pyclient
Requires-Dist: myproxyclient
Requires-Dist: pyyaml
Requires-Dist: pandas
Provides-Extra: deploy
Requires-Dist: twine (>=1.11.0) ; extra == 'deploy'
Requires-Dist: setuptools (>=38.6.0) ; extra == 'deploy'
Requires-Dist: wheel (>=0.31.0) ; extra == 'deploy'
Provides-Extra: dev
Requires-Dist: flake8 ; extra == 'dev'
Requires-Dist: black ; extra == 'dev'
Requires-Dist: isort ; extra == 'dev'
Requires-Dist: codecov ; extra == 'dev'
Requires-Dist: pytest-cov ; extra == 'dev'
Requires-Dist: pytest (>=4.0) ; extra == 'dev'
Requires-Dist: pytest-mock ; extra == 'dev'
Requires-Dist: sphinx (>=1.4) ; extra == 'dev'
Requires-Dist: sphinx-rtd-theme ; extra == 'dev'
Requires-Dist: sphinx-click ; extra == 'dev'
Requires-Dist: twine (>=1.11.0) ; extra == 'dev'
Requires-Dist: setuptools (>=38.6.0) ; extra == 'dev'
Requires-Dist: wheel (>=0.31.0) ; extra == 'dev'
Provides-Extra: docs
Requires-Dist: sphinx (>=1.4) ; extra == 'docs'
Requires-Dist: sphinx-rtd-theme ; extra == 'docs'
Requires-Dist: sphinx-click ; extra == 'docs'
Provides-Extra: tests
Requires-Dist: codecov ; extra == 'tests'
Requires-Dist: pytest-cov ; extra == 'tests'
Requires-Dist: pytest (>=4.0) ; extra == 'tests'
Requires-Dist: pytest-mock ; extra == 'tests'
